README.md
setup.py
apollo_client_py.egg-info/PKG-INFO
apollo_client_py.egg-info/SOURCES.txt
apollo_client_py.egg-info/dependency_links.txt
apollo_client_py.egg-info/not-zip-safe
apollo_client_py.egg-info/requires.txt
apollo_client_py.egg-info/top_level.txt
pyapollo/__init__.py
pyapollo/apollo_client.py
pyapollo/main.py