Metadata-Version: 2.1
Name: apollo-client-py
Version: 0.1.0
Summary: a client for apollo - fix
Home-page: https://github.com/red-butterfly/pyapollo
Author: RedButterfly
Author-email: hanfei1009@126.com
License: UNKNOWN
Platform: any
Classifier: Programming Language :: Python :: 3
Classifier: Programming Language :: Python :: 2.7
